apc_switched_rack_pdu_control_panel/__init__.py
apc_switched_rack_pdu_control_panel/forms.py
apc_switched_rack_pdu_control_panel/jinja2_hash_filter.py
apc_switched_rack_pdu_control_panel/views.py
apc_switched_rack_pdu_control_panel/static/css/lib/bootstrap.min.css
apc_switched_rack_pdu_control_panel/static/js/lib/bootstrap.bundle.min.js
apc_switched_rack_pdu_control_panel/static/js/lib/clipboard.min.js
apc_switched_rack_pdu_control_panel/static/js/lib/color-modes.js
apc_switched_rack_pdu_control_panel/templates/index.html.j2
apc_switched_rack_pdu_control_panel/templates/svg_symbols.j2
apc_switched_rack_pdu_control_panel/templates/system_table.html.j2
apc_switched_rack_pdu_control_panel-0.2.4.dist-info/METADATA
apc_switched_rack_pdu_control_panel-0.2.4.dist-info/WHEEL
apc_switched_rack_pdu_control_panel-0.2.4.dist-info/top_level.txt
apc_switched_rack_pdu_control_panel-0.2.4.dist-info/RECORD
