Metadata-Version: 2.4
Name: apc_switched_rack_pdu_control_panel
Version: 0.2.4
Summary: APC switched rack PDU control panel
Author-email: Christian Schürmann <spike@fedoraproject.org>
Project-URL: Homepage, https://github.com/spike77453/apc-switched-rack-pdu-control-panel
Project-URL: Repository, https://github.com/spike77453/apc-switched-rack-pdu-control-panel.git
Classifier: Development Status :: 4 - Beta
Classifier: Environment :: Web Environment
Classifier: Framework :: Flask
Classifier: Intended Audience :: System Administrators
Classifier: Operating System :: POSIX :: Linux
Classifier: Programming Language :: Python
Classifier: Programming Language :: Python :: 3
Classifier: Programming Language :: Python :: 3.10
Classifier: Programming Language :: Python :: 3.11
Classifier: Programming Language :: Python :: 3.12
Classifier: Programming Language :: Python :: 3.13
Classifier: Topic :: System
Classifier: Topic :: System :: Systems Administration
Classifier: Topic :: Utilities
Requires-Python: >=3.10
Requires-Dist: Flask~=3.0
Requires-Dist: ezsnmp==2.*,>=2.1.0a1
Requires-Dist: wtforms~=3.0
